siv/__init__.py
siv/scripts/__init__.py
siv/scripts/parsehlk/__init__.py
siv/scripts/parsehlk/commandline.py
SivScriptsParsehlk-1.2.0.dist-info/LICENSE.txt
SivScriptsParsehlk-1.2.0.dist-info/METADATA
SivScriptsParsehlk-1.2.0.dist-info/WHEEL
SivScriptsParsehlk-1.2.0.dist-info/entry_points.txt
SivScriptsParsehlk-1.2.0.dist-info/top_level.txt
SivScriptsParsehlk-1.2.0.dist-info/RECORD
